wooscloud/__init__.py
wooscloud/client.py
wooscloud/exceptions.py
wooscloud/files.py
wooscloud/models.py
wooscloud/storage.py
wooscloud/webhooks.py
wooscloud-1.2.5.dist-info/METADATA
wooscloud-1.2.5.dist-info/WHEEL
wooscloud-1.2.5.dist-info/top_level.txt
wooscloud-1.2.5.dist-info/RECORD
