Metadata-Version: 2.4
Name: wooscloud
Version: 1.2.5
Summary: Simple, powerful, and scalable cloud storage for Python applications
Home-page: https://github.com/sisi010/wooscloud-storage
Author: WoosCloud Team
Author-email: support@woos-ai.com
Project-URL: Documentation, https://wooscloud-storage-production.up.railway.app/api/docs
Project-URL: Source, https://github.com/sisi010/wooscloud-storage
Project-URL: Bug Reports, https://github.com/sisi010/wooscloud-storage/issues
Keywords: cloud storage database api rest wooscloud
Classifier: Development Status :: 5 - Production/Stable
Classifier: Intended Audience :: Developers
Classifier: Topic :: Software Development :: Libraries :: Python Modules
Classifier: License :: OSI Approved :: MIT License
Classifier: Programming Language :: Python :: 3
Classifier: Programming Language :: Python :: 3.8
Classifier: Programming Language :: Python :: 3.9
Classifier: Programming Language :: Python :: 3.10
Classifier: Programming Language :: Python :: 3.11
Classifier: Programming Language :: Python :: 3.12
Requires-Python: >=3.8
Requires-Dist: requests>=2.31.0
Dynamic: author
Dynamic: author-email
Dynamic: classifier
Dynamic: description
Dynamic: description-content-type
Dynamic: home-page
Dynamic: keywords
Dynamic: project-url
Dynamic: requires-dist
Dynamic: requires-python
Dynamic: summary
